media_hosts/__init__.py
media_hosts/__main__.py
media_hosts/imports.py
media_hosts/utils.py
media_hosts/backends/__init__.py
media_hosts/backends/soundcloud.py
media_hosts/backends/youtube.py
media_hosts-0.5.dist-info/DESCRIPTION.rst
media_hosts-0.5.dist-info/METADATA
media_hosts-0.5.dist-info/RECORD
media_hosts-0.5.dist-info/WHEEL
media_hosts-0.5.dist-info/metadata.json
media_hosts-0.5.dist-info/top_level.txt
miss/__init__.py
miss/builtins.py
miss/collections.py
miss/datetime.py
miss/functools.py
miss/identity.py
miss/lazy.py
miss/list.py
miss/math.py
miss/namespace.py
miss/six.py
miss/str.py
