Metadata-Version: 2.0
Name: media-hosts
Version: 0.5
Summary: Gets media info from sites like Youtube and Soundcloud
Home-page: https://github.com/Changaco/python-media-hosts
Author: Changaco
Author-email: changaco ατ changaco δοτ net
License: CC0
Platform: UNKNOWN
Requires-Dist: miss (>=0.3)
Requires-Dist: requests
